{
  "MetaData": {
    "Schema": {
      "ManagerName": "AddonSchemaManager",
      "UId": "5f11b37e-5485-4f38-bed9-d9d7bcc0f4f8",
      "A2": "UsrRealtyBusinessRule",
      "A5": "05102a8e-f72e-478a-9b07-6ef339ea400e",
      "B1": [],
      "B2": [],
      "B3": [],
      "B6": "eea181bb-0781-44f3-b136-01d6b9c7e796",
      "B8": "8.2.1.5405",
      "AD1": "9a0658cb-9f2b-429c-b92e-1cd38a5d7a21",
      "AD2": "EntitySchemaManager",
      "AD3": "BusinessRule",
      "AD5": "3a2d6f51-1bfc-4c17-aacb-b53de4866b7c",
      "AD4": {
        "JI0": "Terrasoft.Core.BusinessRules.BusinessRules",
        "BRS1": [
          {
            "JI0": "Terrasoft.Core.BusinessRules.BusinessRule",
            "UId": "624645fe-483c-b082-4263-15a7abbd79b7",
            "BR1": [
              {
                "JI0": "Terrasoft.Core.BusinessRules.Models.BusinessRuleCase",
                "UId": "12e88146-e853-01f2-b27f-57b9be6fd0bd",
                "BRC2": [
                  {
                    "JI0": "Terrasoft.Core.BusinessRules.Models.Actions.BusinessRuleActionSetFilter",
                    "UId": "4925940e-ae39-7147-8c35-5a17201865ea",
                    "BRA2": {
                      "JI0": "Terrasoft.Core.BusinessRules.Models.Expressions.BusinessRuleAttributeExpression",
                      "UId": "6d6da1ad-3345-75e2-8b13-fc667a5cb143",
                      "BRX1": "UsrManager"
                    },
                    "BRA3": {
                      "JI0": "Terrasoft.Core.BusinessRules.Models.Expressions.BusinessRuleValueExpression",
                      "UId": "51586f98-5d9d-90bf-f768-e88b5d455907",
                      "BVE1": "{\"items\":{\"2665f724-9954-4a41-96c3-27a093d0016f\":{\"filterType\":4,\"comparisonType\":3,\"isEnabled\":true,\"trimDateTimeParameterToDate\":false,\"leftExpression\":{\"expressionType\":0,\"columnPath\":\"Type\"},\"isAggregative\":false,\"dataValueType\":10,\"referenceSchemaName\":\"ContactType\",\"rightExpressions\":[{\"expressionType\":2,\"parameter\":{\"dataValueType\":10,\"value\":{\"Name\":\"Employee\",\"Id\":\"60733efc-f36b-1410-a883-16d83cab0980\",\"value\":\"60733efc-f36b-1410-a883-16d83cab0980\",\"displayValue\":\"Employee\"}}}]}},\"logicalOperation\":0,\"isEnabled\":true,\"filterType\":6,\"rootSchemaName\":\"Contact\"}"
                    }
                  }
                ]
              }
            ],
            "BR2": [
              {
                "JI0": "Terrasoft.Core.BusinessRules.Models.Trigger",
                "UId": "b646e66b-6daf-2f54-2994-c9f7ef3c6467",
                "BRT2": 2
              }
            ],
            "BR3": "BusinessRule_8da1e88"
          },
          {
            "JI0": "Terrasoft.Core.BusinessRules.BusinessRule",
            "UId": "275deed2-58b3-927c-0deb-d80183398eea",
            "BR1": [
              {
                "JI0": "Terrasoft.Core.BusinessRules.Models.BusinessRuleCase",
                "UId": "4c244741-1ebb-0df5-c2d4-4e54b1bca280",
                "BRC1": {
                  "JI0": "Terrasoft.Core.BusinessRules.Models.Conditions.BusinessRuleGroupCondition",
                  "UId": "2022a49a-c79f-bc04-625c-0151272a0063",
                  "BGC1": 1,
                  "BGC2": [
                    {
                      "JI0": "Terrasoft.Core.BusinessRules.Models.Conditions.BusinessRuleCondition",
                      "UId": "c10397e1-a749-5a8b-d6f8-d44ba66710c8",
                      "BCO1": {
                        "JI0": "Terrasoft.Core.BusinessRules.Models.Expressions.BusinessRuleAttributeExpression",
                        "UId": "cc9c4497-4d1b-d430-7097-fcf56be6d2d3",
                        "BRE1": "Lookup",
                        "BRE2": "AttributeValue",
                        "BRX1": "UsrCountry",
                        "BRX2": "null"
                      },
                      "BCO3": 1
                    }
                  ]
                },
                "BRC2": [
                  {
                    "JI0": "Terrasoft.Core.BusinessRules.Models.Actions.BusinessRuleActionFilterLookup",
                    "UId": "dd6d7da9-36f4-f0ee-5346-be7346056c9c",
                    "BRA2": {
                      "JI0": "Terrasoft.Core.BusinessRules.Models.Expressions.BusinessRuleAttributeExpression",
                      "UId": "7b1c8f5b-fcba-470b-9de4-2398a7bb9a57",
                      "BRX1": "null",
                      "BRX2": "null"
                    },
                    "BRA3": {
                      "JI0": "Terrasoft.Core.BusinessRules.Models.Expressions.BusinessRuleValueExpression",
                      "UId": "b54a281b-d346-41c2-90ab-73a9b98e417c"
                    },
                    "BSFL1": {
                      "JI0": "Terrasoft.Core.BusinessRules.Models.Expressions.BusinessRuleFilterLookupExpression",
                      "UId": "f0d650ce-b75a-4764-9d89-4a7f3407a617",
                      "BRE1": "Lookup",
                      "BRE3": "City",
                      "BVP1": "UsrCity",
                      "BVF1": "Country"
                    },
                    "BSFR1": {
                      "JI0": "Terrasoft.Core.BusinessRules.Models.Expressions.BusinessRuleFilterLookupExpression",
                      "UId": "820b9701-1f93-9078-63a5-db1b2c798677",
                      "BRE1": "Lookup",
                      "BRE3": "Country",
                      "BVP1": "UsrCountry",
                      "BVF1": "null"
                    }
                  }
                ]
              }
            ],
            "BR2": [
              {
                "JI0": "Terrasoft.Core.BusinessRules.Models.Trigger",
                "UId": "81e5fb58-a472-55f2-6279-affb909c9748",
                "BRT2": 2
              },
              {
                "JI0": "Terrasoft.Core.BusinessRules.Models.Trigger",
                "UId": "ba7be180-848f-a528-495a-862088f577dc",
                "BRT1": "UsrCountry"
              }
            ],
            "BR3": "BusinessRule_6de994f"
          },
          {
            "JI0": "Terrasoft.Core.BusinessRules.BusinessRule",
            "UId": "6f80ee21-2539-7ebf-51b4-9451bbe28859",
            "BR1": [
              {
                "JI0": "Terrasoft.Core.BusinessRules.Models.BusinessRuleCase",
                "UId": "0e5de856-f7ed-7a4b-9832-6e2d141cc421",
                "BRC1": {
                  "JI0": "Terrasoft.Core.BusinessRules.Models.Conditions.BusinessRuleCondition",
                  "UId": "f5a30e53-733a-ae23-4451-85c605889110",
                  "BCO1": {
                    "JI0": "Terrasoft.Core.BusinessRules.Models.Expressions.BusinessRuleAttributeExpression",
                    "UId": "4506efed-90be-8673-de92-9744a19fb5d2",
                    "BRE2": "AttributeValue",
                    "BRX1": "UsrCountry"
                  },
                  "BCO2": {
                    "JI0": "Terrasoft.Core.BusinessRules.Models.Expressions.BusinessRuleAttributeExpression",
                    "UId": "edc58473-5649-fb88-0848-cde473de922b",
                    "BRE2": "AttributeValue",
                    "BRX1": "UsrCity.Country"
                  },
                  "BCO3": 3
                },
                "BRC2": [
                  {
                    "JI0": "Terrasoft.Core.BusinessRules.Models.Actions.BusinessRuleActionSetValues",
                    "UId": "7017b8ee-799b-8100-041c-7915ac603419",
                    "BRA2": {
                      "JI0": "Terrasoft.Core.BusinessRules.Models.Expressions.BusinessRuleAttributeExpression",
                      "UId": "9330c788-0e47-48c0-9c98-1490f0e6cf1b",
                      "BRX1": "null",
                      "BRX2": "null"
                    },
                    "BRA3": {
                      "JI0": "Terrasoft.Core.BusinessRules.Models.Expressions.BusinessRuleValueExpression",
                      "UId": "87723716-aa72-4aaf-bdf7-6ef99e86b0cf"
                    },
                    "BSVS1": [
                      {
                        "JI0": "Terrasoft.Core.BusinessRules.Models.Expressions.BusinessRuleSetValueItem",
                        "UId": "b1b6e43a-a612-ab1c-b31e-ef1d5c812388",
                        "BRA2": {
                          "JI0": "Terrasoft.Core.BusinessRules.Models.Expressions.BusinessRuleAttributeExpression",
                          "UId": "a37a5b50-9cc3-bd2b-90a7-0a7a6c18f3e9",
                          "BRE1": "Lookup",
                          "BRX1": "UsrCity",
                          "BRX2": "null"
                        },
                        "BRA3": {
                          "JI0": "Terrasoft.Core.BusinessRules.Models.Expressions.BusinessRuleEmptyValueExpression",
                          "UId": "c2aeef39-85c2-a4c3-e93b-98359d2ff5ba",
                          "BRE1": "Lookup",
                          "BVE1": "00000000-0000-0000-0000-000000000000"
                        }
                      }
                    ]
                  }
                ]
              }
            ],
            "BR2": [
              {
                "JI0": "Terrasoft.Core.BusinessRules.Models.Trigger",
                "UId": "a967bae6-0231-ce32-1c16-83951fd1cfd6",
                "BRT1": "UsrCountry"
              }
            ],
            "BR3": "Autogenerated_275deed2-58b3-927c-0deb-d80183398eea_ClearValue",
            "BR5": "275deed2-58b3-927c-0deb-d80183398eea",
            "BR6": "dd6d7da9-36f4-f0ee-5346-be7346056c9c"
          },
          {
            "JI0": "Terrasoft.Core.BusinessRules.BusinessRule",
            "UId": "9c8eefd0-207b-a8a9-8b9d-3fcac998018c",
            "BR1": [
              {
                "JI0": "Terrasoft.Core.BusinessRules.Models.BusinessRuleCase",
                "UId": "7195cac5-40e8-ee60-a155-7c6767ddd607",
                "BRC1": {
                  "JI0": "Terrasoft.Core.BusinessRules.Models.Conditions.BusinessRuleCondition",
                  "UId": "071ff8ae-0d72-f3cf-6778-4870c7bb3b0f",
                  "BCO1": {
                    "JI0": "Terrasoft.Core.BusinessRules.Models.Expressions.BusinessRuleAttributeExpression",
                    "UId": "1dae7d2b-5228-8a1b-4f50-9228001f1246",
                    "BRE2": "AttributeValue",
                    "BRX1": "UsrCity"
                  },
                  "BCO3": 1
                },
                "BRC2": [
                  {
                    "JI0": "Terrasoft.Core.BusinessRules.Models.Actions.BusinessRuleActionSetValues",
                    "UId": "5bf6828e-baa0-61f1-228d-2517360d1d52",
                    "BRA2": {
                      "JI0": "Terrasoft.Core.BusinessRules.Models.Expressions.BusinessRuleAttributeExpression",
                      "UId": "03adb714-cbee-40d1-9e63-7e45bf097ed6",
                      "BRX1": "null",
                      "BRX2": "null"
                    },
                    "BRA3": {
                      "JI0": "Terrasoft.Core.BusinessRules.Models.Expressions.BusinessRuleValueExpression",
                      "UId": "129f37f9-95df-476c-8b69-61df3b0f17ff"
                    },
                    "BSVS1": [
                      {
                        "JI0": "Terrasoft.Core.BusinessRules.Models.Expressions.BusinessRuleSetValueItem",
                        "UId": "3cdbea48-8307-b254-008e-ad20a8f8c0f5",
                        "BRA2": {
                          "JI0": "Terrasoft.Core.BusinessRules.Models.Expressions.BusinessRuleAttributeExpression",
                          "UId": "c6fcffc6-280e-cde7-80e0-d9af76b06105",
                          "BRX1": "UsrCountry",
                          "BRX2": "null"
                        },
                        "BRA3": {
                          "JI0": "Terrasoft.Core.BusinessRules.Models.Expressions.BusinessRuleAttributeExpression",
                          "UId": "1c1a0489-0b4c-aaaa-54c0-ecd5a1153d79",
                          "BRE1": "Lookup",
                          "BRE2": "AttributeValue",
                          "BRE3": "Country",
                          "BRX1": "UsrCity.Country"
                        }
                      }
                    ]
                  }
                ]
              }
            ],
            "BR2": [
              {
                "JI0": "Terrasoft.Core.BusinessRules.Models.Trigger",
                "UId": "efd527a1-25c6-a1ea-fce5-0377fbf42360",
                "BRT1": "UsrCity"
              }
            ],
            "BR3": "Autogenerated_275deed2-58b3-927c-0deb-d80183398eea_PopulateValue",
            "BR5": "275deed2-58b3-927c-0deb-d80183398eea",
            "BR6": "dd6d7da9-36f4-f0ee-5346-be7346056c9c"
          }
        ]
      }
    }
  }
}